.gitignore
LICENSE
Makefile
README.md
pyproject.toml
setup.cfg
setup.py
Blush.egg-info/PKG-INFO
Blush.egg-info/SOURCES.txt
Blush.egg-info/dependency_links.txt
Blush.egg-info/not-zip-safe
Blush.egg-info/requires.txt
Blush.egg-info/top_level.txt
blush/__init__.py
blush/tests/test_core.py